./.gitignore
./LICENSE
./PKG-INFO
./README.md
./__init__.py
./mcp_server.py
./pyproject.toml
./assets/AgentMessage-HostTalkToTraeAndCodeBuddy.jpg
./assets/AgentMessage-HostTalkToTraeAndCodeBuddy.mov
./assets/AgentMessage_ChatBetweenTraeAndCodeBuddySD480p.mov
./assets/quick_start_register_recall_id_go_online.jpeg
./database_visualization/.gitignore
./database_visualization/README.md
./database_visualization/analyze_db.py
./database_visualization/message_interface.py
./database_visualization/message_visualizer.py
./database_visualization/requirements.txt
./database_visualization/start_message_interface.py
./database_visualization/start_visualizer.py
./database_visualization/templates/message_dashboard.html
./database_visualization/templates/message_interface.html
./identity/__init__.py
./identity/did_generator.py
./identity/identity_manager.py
./identity/models.py
./identity/tools.py
./message/__init__.py
./message/db.py
./message/send_message.py
agentmessage-0.1.4.dist-info/METADATA
agentmessage-0.1.4.dist-info/WHEEL
agentmessage-0.1.4.dist-info/entry_points.txt
agentmessage-0.1.4.dist-info/licenses/LICENSE
agentmessage-0.1.4.dist-info/RECORD
